{
	"type": "object",
	"references": {
		"currency": {"title":"Currency", "type":"string", "enum":["AED","AFN","ALL","AMD","ANG","AOA","ARS","AUD","AWG","AZN","BAM","BBD","BDT","BGN","BHD","BIF","BMD","BND","BOB","BRL","BSD","BTN","BWP","BYN","BZD","CAD","CDF","CHF","CLP","CNY","COP","CRC","CUC","CUP","CVE","CZK","DJF","DKK","DOP","DZD","EGP","ERN","ETB","EUR","FJD","FKP","GBP","GEL","GGP","GHS","GIP","GMD","GNF","GTQ","GYD","HKD","HNL","HRK","HTG","HUF","IDR","ILS","IMP","INR","IQD","IRR","ISK","JEP","JMD","JOD","JPY","KES","KGS","KHR","KMF","KPW","KRW","KWD","KYD","KZT","LAK","LBP","LKR","LRD","LSL","LYD","MAD","MDL","MGA","MKD","MMK","MNT","MOP","MRO","MUR","MVR","MWK","MXN","MYR","MZN","NAD","NGN","NIO","NOK","NPR","NZD","OMR","PAB","PEN","PGK","PHP","PKR","PLN","PYG","QAR","RON","RSD","RUB","RWF","SAR","SBD","SCR","SDG","SEK","SGD","SHP","SLL","SOS","SPL","SRD","STD","SVC","SYP","SZL","THB","TJS","TMT","TND","TOP","TRY","TTD","TVD","TWD","TZS","UAH","UGX","USD","UYU","UZS","VEF","VND","VUV","WST","XAF","XCD","XDR","XOF","XPF","YER","ZAR","ZMW","ZWD"]},
		"denominations": {
			"type": "array",
			"items": {
				"type": "object",
				"properties": {
					"_idx_":    {"type":"integer", "readonly": true},
					"id":  		 {"title":"Denomination Id","type":"integer","minimum":0,"maximum":15},
					"enabled":	 {"title":"Enabled/Disabled","type":"boolean"},
					"currency":  {"title":"Denom. Currency", "$ref": "#/references/currency" },
					"value":  	 {"title":"Value","type":"number","minimum":0,"maximum":1000},
					"moneycode": {"title":"Denom. Money Code","type":"string","enum":["1","2","3","4","5","6","7","8"]}
				}
			},
			"minItems": 1,
			"maxItems": 16
		}
	},
	"properties": {
		"CUR":{
			"title": "ABill Currency Description",
			"type": "object",
			"properties": {
				"denominations":{"$ref": "#/references/denominations"}
			}
		}
	}
}
